{
  "$schema": "https://schema.management.azure.com/schemas/2019-04-01/deploymentTemplate.json#",
  "contentVersion": "1.0.0.0",
  "metadata": {
    "_generator": {
      "name": "bicep",
      "version": "0.33.93.31351",
      "templateHash": "12463132913658024991"
    }
  },
  "parameters": {
    "vnetName": {
      "type": "string",
      "defaultValue": "VNET1"
    },
    "vmSubnetName": {
      "type": "string",
      "defaultValue": "VMSubnet"
    },
    "adminUsername": {
      "type": "string",
      "defaultValue": "bob"
    },
    "adminPassword": {
      "type": "securestring"
    },
    "vmSize": {
      "type": "string"
    },
    "osImage": {
      "type": "object"
    }
  },
  "resources": [
    {
      "type": "Microsoft.Network/networkInterfaces",
      "apiVersion": "2023-09-01",
      "name": "vm1NIC",
      "location": "[resourceGroup().location]",
      "properties": {
        "ipConfigurations": [
          {
            "name": "ipconfig1",
            "properties": {
              "subnet": {
                "id": "[resourceId('Microsoft.Network/virtualNetworks/subnets', parameters('vnetName'), parameters('vmSubnetName'))]"
              }
            }
          }
        ]
      }
    },
    {
      "type": "Microsoft.Network/networkInterfaces",
      "apiVersion": "2023-09-01",
      "name": "vm2NIC",
      "location": "[resourceGroup().location]",
      "properties": {
        "ipConfigurations": [
          {
            "name": "ipconfig1",
            "properties": {
              "subnet": {
                "id": "[resourceId('Microsoft.Network/virtualNetworks/subnets', parameters('vnetName'), parameters('vmSubnetName'))]"
              }
            }
          }
        ]
      }
    },
    {
      "type": "Microsoft.Compute/virtualMachines",
      "apiVersion": "2023-09-01",
      "name": "vm1",
      "location": "[resourceGroup().location]",
      "properties": {
        "hardwareProfile": {
          "vmSize": "[parameters('vmSize')]"
        },
        "osProfile": {
          "computerName": "vm1",
          "adminUsername": "[parameters('adminUsername')]",
          "adminPassword": "[parameters('adminPassword')]",
          "linuxConfiguration": "[if(equals(parameters('osImage').publisher, 'Canonical'), createObject('disablePasswordAuthentication', false()), null())]",
          "windowsConfiguration": "[if(equals(parameters('osImage').publisher, 'MicrosoftWindowsServer'), createObject('enableAutomaticUpdates', true()), null())]"
        },
        "storageProfile": {
          "imageReference": "[parameters('osImage')]",
          "osDisk": {
            "createOption": "FromImage"
          }
        },
        "networkProfile": {
          "networkInterfaces": [
            {
              "id": "[resourceId('Microsoft.Network/networkInterfaces', 'vm1NIC')]"
            }
          ]
        }
      },
      "dependsOn": [
        "[resourceId('Microsoft.Network/networkInterfaces', 'vm1NIC')]"
      ]
    },
    {
      "type": "Microsoft.Compute/virtualMachines",
      "apiVersion": "2023-09-01",
      "name": "vm2",
      "location": "[resourceGroup().location]",
      "properties": {
        "hardwareProfile": {
          "vmSize": "[parameters('vmSize')]"
        },
        "osProfile": {
          "computerName": "vm2",
          "adminUsername": "[parameters('adminUsername')]",
          "adminPassword": "[parameters('adminPassword')]",
          "linuxConfiguration": "[if(equals(parameters('osImage').publisher, 'Canonical'), createObject('disablePasswordAuthentication', false()), null())]",
          "windowsConfiguration": "[if(equals(parameters('osImage').publisher, 'MicrosoftWindowsServer'), createObject('enableAutomaticUpdates', true()), null())]"
        },
        "storageProfile": {
          "imageReference": "[parameters('osImage')]",
          "osDisk": {
            "createOption": "FromImage"
          }
        },
        "networkProfile": {
          "networkInterfaces": [
            {
              "id": "[resourceId('Microsoft.Network/networkInterfaces', 'vm2NIC')]"
            }
          ]
        }
      },
      "dependsOn": [
        "[resourceId('Microsoft.Network/networkInterfaces', 'vm2NIC')]"
      ]
    }
  ]
}